pymysql_split_tool/__init__.py
pymysql_split_tool/__main__.py
pymysql_split_tool/controller.py
pymysql_split_tool/db.py
pymysql_split_tool/input.py
pymysql_split_tool-0.5.6.dist-info/LICENSE
pymysql_split_tool-0.5.6.dist-info/METADATA
pymysql_split_tool-0.5.6.dist-info/WHEEL
pymysql_split_tool-0.5.6.dist-info/top_level.txt
pymysql_split_tool-0.5.6.dist-info/RECORD
