Metadata-Version: 2.1
Name: pymysql-split-tool
Version: 0.5.6
Summary: mysql spliting/sharding tools
Home-page: https://github.com/echoma/pymysql_split_tool
Author: Echo Ma
Author-email: fatmck@163.com
License: Apache 2.0
Keywords: mysql spliting or sharding tools
Platform: UNKNOWN
Classifier: Development Status :: 4 - Beta
Classifier: Intended Audience :: Developers
Classifier: Topic :: Database
Classifier: License :: OSI Approved :: Apache Software License
Classifier: Programming Language :: Python :: 2
Classifier: Programming Language :: Python :: 2.6
Classifier: Programming Language :: Python :: 2.7
Classifier: Programming Language :: Python :: 3
Classifier: Programming Language :: Python :: 3.3
Classifier: Programming Language :: Python :: 3.4
Classifier: Programming Language :: Python :: 3.5
Classifier: Programming Language :: Python :: 3.6
Classifier: Programming Language :: Python :: 3.7
Requires-Dist: pymysql
